chattdd/__init__.py
chattdd/cli.py
chattdd/core.py
chattdd/logic.py
chattdd/tools.py
ChatTDD-0.2.10.dist-info/LICENSE
ChatTDD-0.2.10.dist-info/METADATA
ChatTDD-0.2.10.dist-info/WHEEL
ChatTDD-0.2.10.dist-info/entry_points.txt
ChatTDD-0.2.10.dist-info/top_level.txt
ChatTDD-0.2.10.dist-info/RECORD
