Metadata-Version: 2.1
Name: ChatTDD
Version: 0.2.10
Summary: A utility to assist in building Test-Driven Python code using Langchain and OpenAI.
Home-page: https://github.com/shuuse/ChatTDD
Author: Simen Huuse
Author-email: s.huuse+chattdd@gmail.com
License: MIT
Classifier: Programming Language :: Python :: 3.9
Classifier: License :: OSI Approved :: MIT License
License-File: LICENSE
Requires-Dist: click
Requires-Dist: openai >=0.27.0
Requires-Dist: pytest
Requires-Dist: python-dotenv
Requires-Dist: langchain
Requires-Dist: keyring
